neo4j_marshaller/__init__.py
neo4j_marshaller/flask_marshaller.py
neo4j_marshaller/neo4j_driver.py
neo4j_marshaller/neo4j_marshaller.py
neo4j_marshaller/utils.py
neo4j_marshaller-0.0.1.dist-info/LICENSE
neo4j_marshaller-0.0.1.dist-info/METADATA
neo4j_marshaller-0.0.1.dist-info/WHEEL
neo4j_marshaller-0.0.1.dist-info/top_level.txt
neo4j_marshaller-0.0.1.dist-info/RECORD
