Metadata-Version: 2.1
Name: neo4j-marshaller
Version: 0.0.1
Summary: Simplified Neo4J Cypher Query execution
Home-page: https://github.com/arunsundaram50/neo4j-marshaller.git
Author: Arun Sundaram
Author-email: arun_co@yahoo.com
License-File: LICENSE
Requires-Dist: neo4j
